paramaterial/__init__.py
paramaterial/aggregating.py
paramaterial/example.py
paramaterial/modelling.py
paramaterial/models.py
paramaterial/plotting.py
paramaterial/plug.py
paramaterial/preparing.py
paramaterial/processing.py
paramaterial/receipts.py
paramaterial/screening.py
paramaterial-0.1.3.dist-info/LICENSE
paramaterial-0.1.3.dist-info/METADATA
paramaterial-0.1.3.dist-info/WHEEL
paramaterial-0.1.3.dist-info/top_level.txt
paramaterial-0.1.3.dist-info/RECORD
