Metadata-Version: 2.1
Name: paramaterial
Version: 0.1.3
Summary: Software toolkit for parameterising materials test data. Easily batch process experimental measurements to determine mechanical properties and material model parameters.
Home-page: https://github.com/dan-slater/paramaterial
Author: Daniel Slater
Author-email: danielgslater@gmail.com
Keywords: python,mechanical testing,materials testing,post-processing,stress-strain,flow stress,yield stress,tensile test,strength,elastic modulus,strain,universal testing machine,fitting constitutive model,material model,solid mechanics,materials science,engineering
Classifier: Development Status :: 3 - Alpha
Classifier: Intended Audience :: Education
Classifier: Programming Language :: Python :: 3
Classifier: Operating System :: OS Independent
License-File: LICENSE
Requires-Dist: matplotlib (>=3.5.2)
Requires-Dist: pandas (>=1.4.4)
Requires-Dist: tqdm (>=4.62.3)
Requires-Dist: numpy (>=1.22.4)
Requires-Dist: scipy (>=1.7.3)
Requires-Dist: jinja2 (>=3.1.2)
Requires-Dist: seaborn (>=0.11.2)
Requires-Dist: pypdf2 (>=2.10.9)
Requires-Dist: svglib (>=1.4.1)
Requires-Dist: reportlab (>=3.5.67)
Requires-Dist: openpyxl (>=3.1.2)
Requires-Dist: setuptools (>=67.8.0)
Requires-Dist: requests (>=2.29.0)
Requires-Dist: chardet (>=4.0.0)
